odoo8_addon_website_cookie_notice-8.0.2.1.0.99.dev11-py3.8-nspkg.pth
odoo_addons/website_cookie_notice/README.rst
odoo_addons/website_cookie_notice/__init__.py
odoo_addons/website_cookie_notice/__openerp__.py
odoo_addons/website_cookie_notice/controllers/__init__.py
odoo_addons/website_cookie_notice/controllers/main.py
odoo_addons/website_cookie_notice/i18n/bg.po
odoo_addons/website_cookie_notice/i18n/ca.po
odoo_addons/website_cookie_notice/i18n/de.po
odoo_addons/website_cookie_notice/i18n/el_GR.po
odoo_addons/website_cookie_notice/i18n/es.po
odoo_addons/website_cookie_notice/i18n/fr.po
odoo_addons/website_cookie_notice/i18n/hr.po
odoo_addons/website_cookie_notice/i18n/hr_HR.po
odoo_addons/website_cookie_notice/i18n/it.po
odoo_addons/website_cookie_notice/i18n/pt_BR.po
odoo_addons/website_cookie_notice/i18n/pt_PT.po
odoo_addons/website_cookie_notice/i18n/ru.po
odoo_addons/website_cookie_notice/i18n/sl.po
odoo_addons/website_cookie_notice/i18n/website_cookie_notice.pot
odoo_addons/website_cookie_notice/static/description/icon.png
odoo_addons/website_cookie_notice/static/src/js/accept_cookies.js
odoo_addons/website_cookie_notice/views/website.xml
odoo8_addon_website_cookie_notice-8.0.2.1.0.99.dev11.dist-info/METADATA
odoo8_addon_website_cookie_notice-8.0.2.1.0.99.dev11.dist-info/WHEEL
odoo8_addon_website_cookie_notice-8.0.2.1.0.99.dev11.dist-info/namespace_packages.txt
odoo8_addon_website_cookie_notice-8.0.2.1.0.99.dev11.dist-info/top_level.txt
odoo8_addon_website_cookie_notice-8.0.2.1.0.99.dev11.dist-info/RECORD
